<?xml version="1.0" standalone="yes"?>
<?xml-stylesheet href="x2script.xsl" type="text/xsl"?>
<!-- Generated using X-Studio -->
<script>
	<name>Mayhem.Task.OCVInvader.Leader</name>
	<version>15</version>
	<engineversion>50</engineversion>
	<description></description>
	<arguments />
	<sourcetext>
		<line linenr="001" indent="" />
		<line linenr="002" indent="">
			<comment>* Task 0.</comment>
		</line>
		<line linenr="003" indent="" />
		<line linenr="004" indent="">
			<comment>* OCV invades all sectors and put Xenon stations in them, leading to new Xenon invasions.</comment>
		</line>
		<line linenr="005" indent="">
			<comment>* in Zero Hour mod they slowly spread out from the OCV portal and don't focus on higher abnormal signal sectors</comment>
		</line>
		<line linenr="006" indent="" />
		<line linenr="007" indent="">
			<comment>* Zero Hour: hard difficulty modifies OCV deep strike invasion chance and galaxy range</comment>
		</line>
		<line linenr="008" indent="">
			<var>WaitForUniverseGeneration</var>
			<text>:</text>
		</line>
		<line linenr="009" indent="">
			<var>$startingOptionsDone</var>
			<text> </text>
			<text>=</text>
			<text> </text>
			<text>get</text>
			<text> </text>
			<text>global</text>
			<text> </text>
			<text>variable</text>
			<text>:</text>
			<text> </text>
			<text>name</text>
			<text>=</text>
			<text>'mayhem_startingOptionDone'</text>
		</line>
		<line linenr="010" indent="">
			<text>if</text>
			<text> </text>
			<text>!</text>
			<var>$startingOptionsDone</var>
		</line>
		<line linenr="011" indent="&#160;" interruptable="@">
			<text>=</text>
			<text> </text>
			<text>wait</text>
			<text> </text>
			<var>60000</var>
			<text> </text>
			<text>ms</text>
		</line>
		<line linenr="012" indent="&#160;">
			<text>goto</text>
			<text> </text>
			<text>label</text>
			<text> </text>
			<var>WaitForUniverseGeneration</var>
			<text>:</text>
		</line>
		<line linenr="013" indent="">
			<text>end</text>
		</line>
		<line linenr="014" indent="">
			<var>$answers</var>
			<text> </text>
			<text>=</text>
			<text> </text>
			<text>get</text>
			<text> </text>
			<text>global</text>
			<text> </text>
			<text>variable</text>
			<text>:</text>
			<text> </text>
			<text>name</text>
			<text>=</text>
			<text>'mayhem_startingOptionAnswers'</text>
		</line>
		<line linenr="015" indent="">
			<var>$difficulty</var>
			<text> </text>
			<text>=</text>
			<text> </text>
			<text>table</text>
			<text> </text>
			<text>get</text>
			<text> </text>
			<var>$answers</var>
			<text> </text>
			<text>(</text>
			<text> </text>
			<text>'ocvDifficulty'</text>
			<text> </text>
			<text>)</text>
		</line>
		<line linenr="016" indent="" />
		<line linenr="017" indent="">
			<text>while</text>
			<text> </text>
			<var>[THIS]</var>
			<text>-&gt;</text>
			<text> </text>
			<text>exists</text>
		</line>
		<line linenr="018" indent="&#160;" />
		<line linenr="019" indent="&#160;">
			<var>Restart</var>
			<text>:</text>
		</line>
		<line linenr="020" indent="&#160;" />
		<line linenr="021" indent="&#160;">
			<text>if</text>
			<text> </text>
			<text>is</text>
			<text> </text>
			<text>a</text>
			<text> </text>
			<text>new</text>
			<text> </text>
			<text>script</text>
			<text> </text>
			<text>version</text>
			<text> </text>
			<text>available</text>
		</line>
		<line linenr="022" indent="&#160;&#160;">
			<var>$scriptName</var>
			<text> </text>
			<text>=</text>
			<text> </text>
			<text>get</text>
			<text> </text>
			<text>script</text>
			<text> </text>
			<text>name</text>
		</line>
		<line linenr="023" indent="&#160;&#160;">
			<var>$taskID</var>
			<text> </text>
			<text>=</text>
			<text> </text>
			<text>get</text>
			<text> </text>
			<text>task</text>
			<text> </text>
			<text>ID</text>
		</line>
		<line linenr="024" indent="&#160;&#160;" interruptable="@">
			<text>START</text>
			<text> </text>
			<var>[NULL]</var>
			<text>-&gt;</text>
			<text> </text>
			<text>call</text>
			<text> </text>
			<text>script</text>
			<text> </text>
			<call>Lib.Gen.RunScriptWhenFinished</call>
			<text> </text>
			<text>:</text>
			<text> </text>
			<text>ScriptName</text>
			<text>=</text>
			<var>$scriptName</var>
			<text> </text>
			<text>TaskWatch</text>
			<text>=</text>
			<var>$taskID</var>
			<text> </text>
			<text>TaskRun</text>
			<text>=</text>
			<var>$taskID</var>
			<text> </text>
			<text>ObjectWatch</text>
			<text>=</text>
			<var>[THIS]</var>
			<text> </text>
			<text>ObjectRun</text>
			<text>=</text>
			<var>[THIS]</var>
			<text> </text>
			<text>arg1</text>
			<text>=</text>
			<var>null</var>
			<text> </text>
			<text>arg2</text>
			<text>=</text>
			<var>null</var>
			<text> </text>
			<text>arg3</text>
			<text>=</text>
			<var>null</var>
			<text> </text>
			<text>arg4</text>
			<text>=</text>
			<var>null</var>
			<text> </text>
			<text>arg5</text>
			<text>=</text>
			<var>null</var>
		</line>
		<line linenr="025" indent="&#160;&#160;">
			<text>return</text>
			<text> </text>
			<var>null</var>
		</line>
		<line linenr="026" indent="&#160;">
			<text>end</text>
		</line>
		<line linenr="027" indent="&#160;" />
		<line linenr="028" indent="&#160;" interruptable="@">
			<text>=</text>
			<text> </text>
			<text>wait</text>
			<text> </text>
			<text>randomly</text>
			<text> </text>
			<text>from</text>
			<text> </text>
			<var>3000</var>
			<text> </text>
			<text>to</text>
			<text> </text>
			<var>4000</var>
			<text> </text>
			<text>ms</text>
		</line>
		<line linenr="029" indent="&#160;" />
		<line linenr="030" indent="&#160;">
			<var>$OCVgrinding</var>
			<text> </text>
			<text>=</text>
			<text> </text>
			<text>get</text>
			<text> </text>
			<text>global</text>
			<text> </text>
			<text>variable</text>
			<text>:</text>
			<text> </text>
			<text>name</text>
			<text>=</text>
			<text>'ZH_OCVgrinding'</text>
		</line>
		<line linenr="031" indent="&#160;" />
		<line linenr="032" indent="&#160;">
			<var>$rng</var>
			<text> </text>
			<text>=</text>
			<text> </text>
			<text>random</text>
			<text> </text>
			<text>value</text>
			<text> </text>
			<text>between</text>
			<text> </text>
			<var>1</var>
			<text> </text>
			<text>and</text>
			<text> </text>
			<var>100</var>
		</line>
		<line linenr="033" indent="&#160;">
			<text>do</text>
			<text> </text>
			<text>if</text>
			<text> </text>
			<var>$OCVgrinding</var>
		</line>
		<line linenr="034" indent="&#160;&#160;">
			<comment>* no deep strikes if the OCV is grinding</comment>
		</line>
		<line linenr="035" indent="&#160;&#160;">
			<var>$rng</var>
			<text> </text>
			<text>=</text>
			<text> </text>
			<var>1</var>
		</line>
		<line linenr="036" indent="&#160;">
			<text>if</text>
			<text> </text>
			<var>$difficulty</var>
			<text> </text>
			<text>&gt;=</text>
			<text> </text>
			<var>2</var>
		</line>
		<line linenr="037" indent="&#160;&#160;">
			<var>$rng</var>
			<text> </text>
			<text>=</text>
			<text> </text>
			<var>$rng</var>
			<text> </text>
			<text>+</text>
			<text> </text>
			<var>20</var>
		</line>
		<line linenr="038" indent="&#160;">
			<text>else</text>
			<text> </text>
			<text>if</text>
			<text> </text>
			<var>$difficulty</var>
			<text> </text>
			<text>==</text>
			<text> </text>
			<var>0</var>
		</line>
		<line linenr="039" indent="&#160;&#160;">
			<text>skip</text>
			<text> </text>
			<text>if</text>
			<text> </text>
			<text>random</text>
			<text> </text>
			<text>value</text>
			<text> </text>
			<text>from</text>
			<text> </text>
			<text>zero</text>
			<text> </text>
			<text>to</text>
			<text> </text>
			<var>3</var>
		</line>
		<line linenr="040" indent="&#160;&#160;&#160;">
			<var>$rng</var>
			<text> </text>
			<text>=</text>
			<text> </text>
			<var>1</var>
		</line>
		<line linenr="041" indent="&#160;">
			<text>end</text>
		</line>
		<line linenr="042" indent="&#160;">
			<text>if</text>
			<text> </text>
			<var>$rng</var>
			<text> </text>
			<text>&gt;=</text>
			<text> </text>
			<var>90</var>
		</line>
		<line linenr="043" indent="&#160;&#160;">
			<var>$jumps</var>
			<text> </text>
			<text>=</text>
			<text> </text>
			<var>8</var>
		</line>
		<line linenr="044" indent="&#160;">
			<text>else</text>
			<text> </text>
			<text>if</text>
			<text> </text>
			<var>$rng</var>
			<text> </text>
			<text>&gt;=</text>
			<text> </text>
			<var>80</var>
		</line>
		<line linenr="045" indent="&#160;&#160;">
			<var>$jumps</var>
			<text> </text>
			<text>=</text>
			<text> </text>
			<var>4</var>
		</line>
		<line linenr="046" indent="&#160;">
			<text>else</text>
			<text> </text>
			<text>if</text>
			<text> </text>
			<var>$rng</var>
			<text> </text>
			<text>&gt;=</text>
			<text> </text>
			<var>60</var>
		</line>
		<line linenr="047" indent="&#160;&#160;">
			<var>$jumps</var>
			<text> </text>
			<text>=</text>
			<text> </text>
			<var>2</var>
		</line>
		<line linenr="048" indent="&#160;">
			<text>else</text>
		</line>
		<line linenr="049" indent="&#160;&#160;">
			<var>$jumps</var>
			<text> </text>
			<text>=</text>
			<text> </text>
			<var>1</var>
		</line>
		<line linenr="050" indent="&#160;">
			<text>end</text>
		</line>
		<line linenr="051" indent="&#160;">
			<text>if</text>
			<text> </text>
			<var>$difficulty</var>
			<text> </text>
			<text>&gt;=</text>
			<text> </text>
			<var>2</var>
		</line>
		<line linenr="052" indent="&#160;&#160;">
			<var>$jumps</var>
			<text> </text>
			<text>=</text>
			<text> </text>
			<var>$jumps</var>
			<text> </text>
			<text>+</text>
			<text> </text>
			<var>1</var>
		</line>
		<line linenr="053" indent="&#160;">
			<text>else</text>
			<text> </text>
			<text>if</text>
			<text> </text>
			<var>$difficulty</var>
			<text> </text>
			<text>==</text>
			<text> </text>
			<var>0</var>
		</line>
		<line linenr="054" indent="&#160;&#160;">
			<var>$jumps</var>
			<text> </text>
			<text>=</text>
			<text> </text>
			<var>$jumps</var>
			<text> </text>
			<text>/</text>
			<text> </text>
			<var>2</var>
		</line>
		<line linenr="055" indent="&#160;&#160;">
			<text>skip</text>
			<text> </text>
			<text>if</text>
			<text> </text>
			<var>$jumps</var>
		</line>
		<line linenr="056" indent="&#160;&#160;&#160;">
			<var>$jumps</var>
			<text> </text>
			<text>=</text>
			<text> </text>
			<var>1</var>
		</line>
		<line linenr="057" indent="&#160;">
			<text>end</text>
		</line>
		<line linenr="058" indent="&#160;">
			<var>$invasionSector</var>
			<text> </text>
			<text>=</text>
			<text> </text>
			<var>null</var>
		</line>
		<line linenr="059" indent="&#160;">
			<var>SearchSector</var>
			<text>:</text>
		</line>
		<line linenr="060" indent="&#160;">
			<var>$sectors</var>
			<text> </text>
			<text>=</text>
			<text> </text>
			<var>[THIS]</var>
			<text>-&gt;</text>
			<text> </text>
			<text>find</text>
			<text> </text>
			<text>all</text>
			<text> </text>
			<text>sectors</text>
			<text> </text>
			<text>within</text>
			<text> </text>
			<var>$jumps</var>
			<text> </text>
			<text>jumps</text>
			<text>:</text>
			<text> </text>
			<text>Only</text>
			<text> </text>
			<text>known</text>
			<text> </text>
			<text>sectors</text>
			<text>=</text>
			<var>[FALSE]</var>
		</line>
		<line linenr="061" indent="&#160;" interruptable="@">
			<var>$sectors</var>
			<text> </text>
			<text>=</text>
			<text> </text>
			<var>[NULL]</var>
			<text>-&gt;</text>
			<text> </text>
			<text>call</text>
			<text> </text>
			<text>script</text>
			<text> </text>
			<call>Joubarbe.Lib.RandomizeArray</call>
			<text> </text>
			<text>:</text>
			<text> </text>
			<text>array</text>
			<text>=</text>
			<var>$sectors</var>
		</line>
		<line linenr="062" indent="&#160;">
			<var>$XS.Iterator1</var>
			<text> </text>
			<text>=</text>
			<text> </text>
			<text>size</text>
			<text> </text>
			<text>of</text>
			<text> </text>
			<text>array</text>
			<text> </text>
			<var>$sectors</var>
		</line>
		<line linenr="063" indent="&#160;&#160;">
			<text>while</text>
			<text> </text>
			<var>$XS.Iterator1</var>
		</line>
		<line linenr="064" indent="&#160;&#160;">
			<text>dec</text>
			<text> </text>
			<var>$XS.Iterator1</var>
		</line>
		<line linenr="065" indent="&#160;&#160;&#160;">
			<var>$sector</var>
			<text> </text>
			<text>=</text>
			<text> </text>
			<var>$sectors</var>
			<text>[</text>
			<var>$XS.Iterator1</var>
			<text>]</text>
		</line>
		<line linenr="066" indent="&#160;&#160;">
			<var>$sector.owner</var>
			<text> </text>
			<text>=</text>
			<text> </text>
			<var>$sector</var>
			<text>-&gt;</text>
			<text> </text>
			<text>get</text>
			<text> </text>
			<text>owner</text>
			<text> </text>
			<text>race</text>
		</line>
		<line linenr="067" indent="&#160;&#160;&#160;">
			<text>do</text>
			<text> </text>
			<text>if</text>
			<text> </text>
			<var>$sector.owner</var>
			<text> </text>
			<text>==</text>
			<text> </text>
			<var>[Xenon]</var>
		</line>
		<line linenr="068" indent="&#160;&#160;&#160;">
			<text>continue</text>
		</line>
		<line linenr="069" indent="&#160;&#160;&#160;&#160;">
			<text>if</text>
			<text> </text>
			<var>$jumps</var>
			<text> </text>
			<text>&gt;</text>
			<text> </text>
			<var>1</var>
		</line>
		<line linenr="070" indent="&#160;&#160;&#160;&#160;">
			<comment>* the random long range strikes cannot target the player if his empire is still small. Otherwise bad luck could make it impossible to prevent</comment>
		</line>
		<line linenr="071" indent="&#160;&#160;&#160;&#160;">
			<text>if</text>
			<text> </text>
			<var>$sector.owner</var>
			<text> </text>
			<text>==</text>
			<text> </text>
			<var>[Player]</var>
		</line>
		<line linenr="072" indent="&#160;&#160;&#160;&#160;&#160;" interruptable="@">
			<var>$plSectors</var>
			<text> </text>
			<text>=</text>
			<text> </text>
			<var>[NULL]</var>
			<text>-&gt;</text>
			<text> </text>
			<text>call</text>
			<text> </text>
			<text>script</text>
			<text> </text>
			<call>Mayhem.GetOwnedSectors</call>
			<text> </text>
			<text>:</text>
			<text> </text>
			<text>race</text>
			<text>=</text>
			<var>[Player]</var>
			<text> </text>
			<text>randomize</text>
			<text>=</text>
			<var>[FALSE]</var>
		</line>
		<line linenr="073" indent="&#160;&#160;&#160;">
			<var>$plSectors.s</var>
			<text> </text>
			<text>=</text>
			<text> </text>
			<text>size</text>
			<text> </text>
			<text>of</text>
			<text> </text>
			<text>array</text>
			<text> </text>
			<var>$plSectors</var>
		</line>
		<line linenr="074" indent="&#160;&#160;">
			<text>skip</text>
			<text> </text>
			<text>if</text>
			<text> </text>
			<var>$plSectors.s</var>
			<text> </text>
			<text>&gt;</text>
			<text> </text>
			<var>9</var>
		</line>
		<line linenr="075" indent="&#160;&#160;">
			<text>continue</text>
		</line>
		<line linenr="076" indent="&#160;&#160;">
			<text>end</text>
		</line>
		<line linenr="077" indent="&#160;&#160;">
			<text>end</text>
		</line>
		<line linenr="078" indent="&#160;&#160;&#160;">
			<text>gosub</text>
			<text> </text>
			<var>CheckTerraformerCapships</var>
			<text>:</text>
		</line>
		<line linenr="079" indent="&#160;&#160;">
			<comment>* we don't want too many invader fleets in one sector (undefeatable doomstack) unless the OCV is grinding</comment>
		</line>
		<line linenr="080" indent="&#160;&#160;">
			<text>do</text>
			<text> </text>
			<text>if</text>
			<text> </text>
			<var>$terraformerCapships.s</var>
			<text> </text>
			<text>&gt;</text>
			<text> </text>
			<var>2</var>
			<text> </text>
			<text>AND</text>
			<text> </text>
			<text>!</text>
			<var>$OCVgrinding</var>
		</line>
		<line linenr="081" indent="&#160;">
			<text>continue</text>
		</line>
		<line linenr="082" indent="&#160;">
			<var>$invasionSector</var>
			<text> </text>
			<text>=</text>
			<text> </text>
			<var>$sector</var>
		</line>
		<line linenr="083" indent="&#160;&#160;">
			<text>break</text>
		</line>
		<line linenr="084" indent="&#160;&#160;&#160;">
			<text>end</text>
		</line>
		<line linenr="085" indent="&#160;&#160;&#160;">
			<text>if</text>
			<text> </text>
			<text>!</text>
			<var>$invasionSector</var>
		</line>
		<line linenr="086" indent="&#160;&#160;">
			<text>if</text>
			<text> </text>
			<var>$jumps</var>
			<text> </text>
			<text>&gt;</text>
			<text> </text>
			<var>30</var>
		</line>
		<line linenr="087" indent="&#160;&#160;" interruptable="@">
			<text>=</text>
			<text> </text>
			<var>[THIS]</var>
			<text>-&gt;</text>
			<text> </text>
			<text>call</text>
			<text> </text>
			<text>script</text>
			<text> </text>
			<call>!fight.defend.sector</call>
			<text> </text>
			<text>:</text>
			<text> </text>
			<text>sector</text>
			<text>=</text>
			<var>[SECTOR]</var>
			<text> </text>
			<text>timeoutSeconds</text>
			<text>=</text>
			<var>1800</var>
		</line>
		<line linenr="088" indent="&#160;&#160;">
			<text>goto</text>
			<text> </text>
			<text>label</text>
			<text> </text>
			<var>Restart</var>
			<text>:</text>
		</line>
		<line linenr="089" indent="&#160;">
			<text>end</text>
		</line>
		<line linenr="090" indent="&#160;">
			<text>inc</text>
			<text> </text>
			<var>$jumps</var>
		</line>
		<line linenr="091" indent="&#160;">
			<text>goto</text>
			<text> </text>
			<text>label</text>
			<text> </text>
			<var>SearchSector</var>
			<text>:</text>
		</line>
		<line linenr="092" indent="&#160;&#160;">
			<text>end</text>
		</line>
		<line linenr="093" indent="&#160;&#160;" />
		<line linenr="094" indent="&#160;">
			<text>while</text>
			<text> </text>
			<var>[SECTOR]</var>
			<text> </text>
			<text>!=</text>
			<text> </text>
			<var>$invasionSector</var>
		</line>
		<line linenr="095" indent="&#160;" interruptable="@">
			<text>=</text>
			<text> </text>
			<var>[THIS]</var>
			<text>-&gt;</text>
			<text> </text>
			<text>call</text>
			<text> </text>
			<text>script</text>
			<text> </text>
			<call>!move.movetosector</call>
			<text> </text>
			<text>:</text>
			<text> </text>
			<text>targetsector</text>
			<text>=</text>
			<var>$invasionSector</var>
		</line>
		<line linenr="096" indent="&#160;" interruptable="@">
			<text>=</text>
			<text> </text>
			<text>wait</text>
			<text> </text>
			<var>1000</var>
			<text> </text>
			<text>ms</text>
		</line>
		<line linenr="097" indent="&#160;">
			<text>end</text>
		</line>
		<line linenr="098" indent="&#160;" />
		<line linenr="099" indent="&#160;&#160;">
			<comment>* we have reached our invasion target. Now we check if any other invaders came here before us</comment>
		</line>
		<line linenr="100" indent="&#160;&#160;">
			<text>gosub</text>
			<text> </text>
			<var>CheckTerraformerCapships</var>
			<text>:</text>
		</line>
		<line linenr="101" indent="&#160;&#160;&#160;">
			<var>$XS.Iterator2</var>
			<text> </text>
			<text>=</text>
			<text> </text>
			<text>size</text>
			<text> </text>
			<text>of</text>
			<text> </text>
			<text>array</text>
			<text> </text>
			<var>$terraformerCapships</var>
		</line>
		<line linenr="102" indent="&#160;&#160;&#160;">
			<text>while</text>
			<text> </text>
			<var>$XS.Iterator2</var>
		</line>
		<line linenr="103" indent="&#160;&#160;&#160;&#160;">
			<text>dec</text>
			<text> </text>
			<var>$XS.Iterator2</var>
		</line>
		<line linenr="104" indent="&#160;&#160;&#160;">
			<var>$ship</var>
			<text> </text>
			<text>=</text>
			<text> </text>
			<var>$terraformerCapships</var>
			<text>[</text>
			<var>$XS.Iterator2</var>
			<text>]</text>
		</line>
		<line linenr="105" indent="&#160;&#160;&#160;&#160;" interruptable="@">
			<text>=</text>
			<text> </text>
			<text>wait</text>
			<text> </text>
			<var>100</var>
			<text> </text>
			<text>ms</text>
		</line>
		<line linenr="106" indent="&#160;&#160;">
			<text>if</text>
			<text> </text>
			<text>random</text>
			<text> </text>
			<text>value</text>
			<text> </text>
			<text>from</text>
			<text> </text>
			<text>zero</text>
			<text> </text>
			<text>to</text>
			<text> </text>
			<var>$terraformerCapships.s</var>
		</line>
		<line linenr="107" indent="&#160;">
			<comment>* there is always a chance to stay, depending on how many capships are already here. But most of the time we do not want more than 1 OCV invader fleet per sector.</comment>
		</line>
		<line linenr="108" indent="&#160;">
			<text>do</text>
			<text> </text>
			<text>if</text>
			<text> </text>
			<var>$ship</var>
			<text>-&gt;</text>
			<text> </text>
			<text>is</text>
			<text> </text>
			<text>script</text>
			<text> </text>
			<call>Mayhem.Task.OCVInvader.Leader</call>
			<text> </text>
			<text>on</text>
			<text> </text>
			<text>stack</text>
			<text> </text>
			<text>of</text>
			<text> </text>
			<text>task</text>
			<text>=</text>
			<var>0</var>
		</line>
		<line linenr="109" indent="&#160;">
			<text>goto</text>
			<text> </text>
			<text>label</text>
			<text> </text>
			<var>SearchSector</var>
			<text>:</text>
		</line>
		<line linenr="110" indent="&#160;">
			<text>do</text>
			<text> </text>
			<text>if</text>
			<text> </text>
			<var>$ship</var>
			<text>-&gt;</text>
			<text> </text>
			<text>is</text>
			<text> </text>
			<text>script</text>
			<text> </text>
			<call>Mayhem.Task.XenonInvader.Leader</call>
			<text> </text>
			<text>on</text>
			<text> </text>
			<text>stack</text>
			<text> </text>
			<text>of</text>
			<text> </text>
			<text>task</text>
			<text>=</text>
			<var>0</var>
		</line>
		<line linenr="111" indent="&#160;">
			<text>goto</text>
			<text> </text>
			<text>label</text>
			<text> </text>
			<var>SearchSector</var>
			<text>:</text>
		</line>
		<line linenr="112" indent="&#160;&#160;">
			<text>end</text>
		</line>
		<line linenr="113" indent="&#160;&#160;">
			<text>end</text>
		</line>
		<line linenr="114" indent="&#160;&#160;&#160;" />
		<line linenr="115" indent="&#160;">
			<var>SearchTarget</var>
			<text>:</text>
		</line>
		<line linenr="116" indent="&#160;">
			<var>$timeout</var>
			<text> </text>
			<text>=</text>
			<text> </text>
			<text>random</text>
			<text> </text>
			<text>value</text>
			<text> </text>
			<text>between</text>
			<text> </text>
			<var>150</var>
			<text> </text>
			<text>and</text>
			<text> </text>
			<var>450</var>
		</line>
		<line linenr="117" indent="&#160;">
			<text>if</text>
			<text> </text>
			<text>not</text>
			<text> </text>
			<var>$OCVgrinding</var>
		</line>
		<line linenr="118" indent="&#160;">
			<comment>* don't waste time when grinding</comment>
		</line>
		<line linenr="119" indent="&#160;">
			<text>skip</text>
			<text> </text>
			<text>if</text>
			<text> </text>
			<var>$target</var>
			<text>-&gt;</text>
			<text> </text>
			<text>exists</text>
		</line>
		<line linenr="120" indent="&#160;" interruptable="@">
			<text>=</text>
			<text> </text>
			<var>[THIS]</var>
			<text>-&gt;</text>
			<text> </text>
			<text>call</text>
			<text> </text>
			<text>script</text>
			<text> </text>
			<call>!fight.defend.sector</call>
			<text> </text>
			<text>:</text>
			<text> </text>
			<text>sector</text>
			<text>=</text>
			<var>[SECTOR]</var>
			<text> </text>
			<text>timeoutSeconds</text>
			<text>=</text>
			<var>$timeout</var>
		</line>
		<line linenr="121" indent="&#160;">
			<text>end</text>
		</line>
		<line linenr="122" indent="&#160;">
			<var>$flags</var>
			<text> </text>
			<text>=</text>
			<text> </text>
			<var>[Find.Nearest]</var>
			<text> </text>
			<text>|</text>
			<text> </text>
			<var>[Find.Enemy]</var>
		</line>
		<line linenr="123" indent="&#160;">
			<comment>* Priorities: Huge ships, Big ships, Factories, Outposts.</comment>
		</line>
		<line linenr="124" indent="&#160;&#160;">
			<comment>* $target = find ship: sector=[SECTOR] class or type=[Huge Ship] race=null flags=$flags refobj=[THIS] maxdist=80000 maxnum=1 refpos=null</comment>
		</line>
		<line linenr="125" indent="&#160;">
			<comment>* = wait 100 ms</comment>
		</line>
		<line linenr="126" indent="&#160;">
			<comment>* skip if $target-&gt; exists</comment>
		</line>
		<line linenr="127" indent="&#160;&#160;">
			<comment>* $target = find ship: sector=[SECTOR] class or type=[Big Ship] race=null flags=$flags refobj=[THIS] maxdist=80000 maxnum=1 refpos=null</comment>
		</line>
		<line linenr="128" indent="&#160;">
			<comment>* = wait 100 ms</comment>
		</line>
		<line linenr="129" indent="&#160;">
			<text>skip</text>
			<text> </text>
			<text>if</text>
			<text> </text>
			<var>$target</var>
			<text>-&gt;</text>
			<text> </text>
			<text>exists</text>
		</line>
		<line linenr="130" indent="&#160;&#160;">
			<var>$target</var>
			<text> </text>
			<text>=</text>
			<text> </text>
			<text>find</text>
			<text> </text>
			<text>station</text>
			<text>:</text>
			<text> </text>
			<text>sector</text>
			<text>=</text>
			<var>[SECTOR]</var>
			<text> </text>
			<text>class</text>
			<text> </text>
			<text>or</text>
			<text> </text>
			<text>type</text>
			<text>=</text>
			<var>[Factory]</var>
			<text> </text>
			<text>race</text>
			<text>=</text>
			<var>null</var>
			<text> </text>
			<text>flags</text>
			<text>=</text>
			<var>$flags</var>
			<text> </text>
			<text>refobj</text>
			<text>=</text>
			<var>[THIS]</var>
			<text> </text>
			<text>maxdist</text>
			<text>=</text>
			<var>300000</var>
			<text> </text>
			<text>maxnum</text>
			<text>=</text>
			<var>1</var>
			<text> </text>
			<text>refpos</text>
			<text>=</text>
			<var>null</var>
		</line>
		<line linenr="131" indent="&#160;&#160;" interruptable="@">
			<text>=</text>
			<text> </text>
			<text>wait</text>
			<text> </text>
			<var>100</var>
			<text> </text>
			<text>ms</text>
		</line>
		<line linenr="132" indent="&#160;">
			<text>skip</text>
			<text> </text>
			<text>if</text>
			<text> </text>
			<var>$target</var>
			<text>-&gt;</text>
			<text> </text>
			<text>exists</text>
		</line>
		<line linenr="133" indent="&#160;&#160;">
			<var>$target</var>
			<text> </text>
			<text>=</text>
			<text> </text>
			<text>find</text>
			<text> </text>
			<text>station</text>
			<text>:</text>
			<text> </text>
			<text>sector</text>
			<text>=</text>
			<var>[SECTOR]</var>
			<text> </text>
			<text>class</text>
			<text> </text>
			<text>or</text>
			<text> </text>
			<text>type</text>
			<text>=</text>
			<var>null</var>
			<text> </text>
			<text>race</text>
			<text>=</text>
			<var>null</var>
			<text> </text>
			<text>flags</text>
			<text>=</text>
			<var>$flags</var>
			<text> </text>
			<text>refobj</text>
			<text>=</text>
			<var>[THIS]</var>
			<text> </text>
			<text>maxdist</text>
			<text>=</text>
			<var>300000</var>
			<text> </text>
			<text>maxnum</text>
			<text>=</text>
			<var>1</var>
			<text> </text>
			<text>refpos</text>
			<text>=</text>
			<var>null</var>
		</line>
		<line linenr="134" indent="&#160;&#160;" />
		<line linenr="135" indent="&#160;&#160;&#160;">
			<text>if</text>
			<text> </text>
			<var>$target</var>
			<text>-&gt;</text>
			<text> </text>
			<text>exists</text>
		</line>
		<line linenr="136" indent="&#160;&#160;&#160;" interruptable="@">
			<text>=</text>
			<text> </text>
			<var>[THIS]</var>
			<text>-&gt;</text>
			<text> </text>
			<text>call</text>
			<text> </text>
			<text>script</text>
			<text> </text>
			<call>!fight.attack.object</call>
			<text> </text>
			<text>:</text>
			<text> </text>
			<text>target</text>
			<text>=</text>
			<var>$target</var>
			<text> </text>
			<text>follow</text>
			<text>=</text>
			<var>[FALSE]</var>
			<text> </text>
			<text>onlyShields</text>
			<text>=</text>
			<var>[FALSE]</var>
			<text> </text>
			<text>timeoutSeconds</text>
			<text>=</text>
			<var>3600</var>
		</line>
		<line linenr="137" indent="&#160;&#160;">
			<text>goto</text>
			<text> </text>
			<text>label</text>
			<text> </text>
			<var>SearchTarget</var>
			<text>:</text>
		</line>
		<line linenr="138" indent="&#160;&#160;">
			<text>else</text>
		</line>
		<line linenr="139" indent="&#160;&#160;&#160;">
			<var>$sector.owner</var>
			<text> </text>
			<text>=</text>
			<text> </text>
			<var>[SECTOR]</var>
			<text>-&gt;</text>
			<text> </text>
			<text>get</text>
			<text> </text>
			<text>owner</text>
			<text> </text>
			<text>race</text>
		</line>
		<line linenr="140" indent="&#160;&#160;">
			<text>if</text>
			<text> </text>
			<var>$sector.owner</var>
			<text> </text>
			<text>!=</text>
			<text> </text>
			<var>[Xenon]</var>
		</line>
		<line linenr="141" indent="&#160;&#160;&#160;">
			<comment>* Also see !station.signal.killed.</comment>
		</line>
		<line linenr="142" indent="&#160;&#160;&#160;" interruptable="@">
			<text>=</text>
			<text> </text>
			<var>[NULL]</var>
			<text>-&gt;</text>
			<text> </text>
			<text>call</text>
			<text> </text>
			<text>script</text>
			<text> </text>
			<call>Mayhem.Conquer</call>
			<text> </text>
			<text>:</text>
			<text> </text>
			<text>sector</text>
			<text>=</text>
			<var>[SECTOR]</var>
			<text> </text>
			<text>raceOrObject</text>
			<text>=</text>
			<var>[Xenon]</var>
		</line>
		<line linenr="143" indent="&#160;&#160;">
			<text>end</text>
		</line>
		<line linenr="144" indent="&#160;&#160;&#160;">
			<text>skip</text>
			<text> </text>
			<text>if</text>
			<text> </text>
			<text>find</text>
			<text> </text>
			<text>station</text>
			<text>:</text>
			<text> </text>
			<text>sector</text>
			<text>=</text>
			<var>[SECTOR]</var>
			<text> </text>
			<text>class</text>
			<text> </text>
			<text>or</text>
			<text> </text>
			<text>type</text>
			<text>=</text>
			<var>{Xenon Station}</var>
			<text> </text>
			<text>race</text>
			<text>=</text>
			<var>[Xenon]</var>
			<text> </text>
			<text>flags</text>
			<text>=</text>
			<var>0</var>
			<text> </text>
			<text>refobj</text>
			<text>=</text>
			<var>null</var>
			<text> </text>
			<text>maxdist</text>
			<text>=</text>
			<var>0</var>
			<text> </text>
			<text>maxnum</text>
			<text>=</text>
			<var>1</var>
			<text> </text>
			<text>refpos</text>
			<text>=</text>
			<var>null</var>
		</line>
		<line linenr="145" indent="&#160;&#160;" interruptable="@">
			<var>$station</var>
			<text> </text>
			<text>=</text>
			<text> </text>
			<var>[NULL]</var>
			<text>-&gt;</text>
			<text> </text>
			<text>call</text>
			<text> </text>
			<text>script</text>
			<text> </text>
			<call>Mayhem.BuildStationAI</call>
			<text> </text>
			<text>:</text>
			<text> </text>
			<text>type</text>
			<text>=</text>
			<var>{Xenon Station}</var>
			<text> </text>
			<text>owner</text>
			<text>=</text>
			<var>[Xenon]</var>
			<text> </text>
			<text>sector</text>
			<text>=</text>
			<var>[SECTOR]</var>
			<text> </text>
			<text>ware</text>
			<text>=</text>
			<var>null</var>
			<text> </text>
			<text>templateItem</text>
			<text>=</text>
			<var>null</var>
		</line>
		<line linenr="146" indent="&#160;">
			<text>if</text>
			<text> </text>
			<var>$OCVgrinding</var>
		</line>
		<line linenr="147" indent="&#160;">
			<comment>* don't waste time when grinding</comment>
		</line>
		<line linenr="148" indent="" interruptable="@">
			<text>=</text>
			<text> </text>
			<var>[THIS]</var>
			<text>-&gt;</text>
			<text> </text>
			<text>call</text>
			<text> </text>
			<text>script</text>
			<text> </text>
			<call>!fight.defend.sector</call>
			<text> </text>
			<text>:</text>
			<text> </text>
			<text>sector</text>
			<text>=</text>
			<var>[SECTOR]</var>
			<text> </text>
			<text>timeoutSeconds</text>
			<text>=</text>
			<var>120</var>
		</line>
		<line linenr="149" indent="">
			<text>else</text>
		</line>
		<line linenr="150" indent="" interruptable="@">
			<text>=</text>
			<text> </text>
			<var>[THIS]</var>
			<text>-&gt;</text>
			<text> </text>
			<text>call</text>
			<text> </text>
			<text>script</text>
			<text> </text>
			<call>!fight.defend.sector</call>
			<text> </text>
			<text>:</text>
			<text> </text>
			<text>sector</text>
			<text>=</text>
			<var>[SECTOR]</var>
			<text> </text>
			<text>timeoutSeconds</text>
			<text>=</text>
			<var>3600</var>
		</line>
		<line linenr="151" indent="">
			<text>end</text>
		</line>
		<line linenr="152" indent="">
			<text>end</text>
		</line>
		<line linenr="153" indent="" />
		<line linenr="154" indent="&#160;">
			<text>end</text>
		</line>
		<line linenr="155" indent="&#160;" />
		<line linenr="156" indent="&#160;">
			<text>return</text>
			<text> </text>
			<var>null</var>
		</line>
		<line linenr="157" indent="&#160;" />
		<line linenr="158" indent="&#160;" />
		<line linenr="159" indent="">
			<var>CheckTerraformerCapships</var>
			<text>:</text>
		</line>
		<line linenr="160" indent="">
			<comment>* Zero Hour: we need to ensure that Terraformer capships tend to spread out and don't create undefeatable doomstacks</comment>
		</line>
		<line linenr="161" indent="" interruptable="@">
			<var>$OCVcapships</var>
			<text> </text>
			<text>=</text>
			<text> </text>
			<var>[NULL]</var>
			<text>-&gt;</text>
			<text> </text>
			<text>call</text>
			<text> </text>
			<text>script</text>
			<text> </text>
			<call>Joubarbe.Lib.GetAllShipsFromSector</call>
			<text> </text>
			<text>:</text>
			<text> </text>
			<text>sector</text>
			<text>=</text>
			<var>$sector</var>
			<text> </text>
			<text>race</text>
			<text>=</text>
			<var>[OCV]</var>
			<text> </text>
			<text>classOrType</text>
			<text>=</text>
			<var>[Huge Ship]</var>
		</line>
		<line linenr="162" indent="" interruptable="@">
			<var>$xenonCapships</var>
			<text> </text>
			<text>=</text>
			<text> </text>
			<var>[NULL]</var>
			<text>-&gt;</text>
			<text> </text>
			<text>call</text>
			<text> </text>
			<text>script</text>
			<text> </text>
			<call>Joubarbe.Lib.GetAllShipsFromSector</call>
			<text> </text>
			<text>:</text>
			<text> </text>
			<text>sector</text>
			<text>=</text>
			<var>$sector</var>
			<text> </text>
			<text>race</text>
			<text>=</text>
			<var>[Xenon]</var>
			<text> </text>
			<text>classOrType</text>
			<text>=</text>
			<var>[Huge Ship]</var>
		</line>
		<line linenr="163" indent="">
			<var>$terraformerCapships</var>
			<text> </text>
			<text>=</text>
			<text> </text>
			<text>join</text>
			<text> </text>
			<text>arrays</text>
			<text>:</text>
			<text> </text>
			<text>first</text>
			<text>=</text>
			<var>$OCVcapships</var>
			<text>,</text>
			<text> </text>
			<text>second</text>
			<text>=</text>
			<var>$xenonCapships</var>
		</line>
		<line linenr="164" indent="">
			<var>$terraformerCapships.s</var>
			<text> </text>
			<text>=</text>
			<text> </text>
			<text>size</text>
			<text> </text>
			<text>of</text>
			<text> </text>
			<text>array</text>
			<text> </text>
			<var>$terraformerCapships</var>
		</line>
		<line linenr="165" indent="">
			<text>endsub</text>
		</line>
	</sourcetext>
	<codearray>
		<sval type="array" size="10">
			<sval type="string" val="Mayhem.Task.OCVInvader.Leader" />
			<sval type="int" val="50" />
			<sval type="string" val="" />
			<sval type="int" val="15" />
			<sval type="int" val="0" />
			<sval type="array" size="25">
				<sval type="string" val="startingOptionsDone" />
				<sval type="string" val="answers" />
				<sval type="string" val="difficulty" />
				<sval type="string" val="scriptName" />
				<sval type="string" val="taskID" />
				<sval type="string" val="OCVgrinding" />
				<sval type="string" val="rng" />
				<sval type="string" val="jumps" />
				<sval type="string" val="invasionSector" />
				<sval type="string" val="sectors" />
				<sval type="string" val="sector" />
				<sval type="string" val="XS.Iterator1" />
				<sval type="string" val="sector.owner" />
				<sval type="string" val="plSectors" />
				<sval type="string" val="plSectors.s" />
				<sval type="string" val="terraformerCapships.s" />
				<sval type="string" val="ship" />
				<sval type="string" val="terraformerCapships" />
				<sval type="string" val="XS.Iterator2" />
				<sval type="string" val="timeout" />
				<sval type="string" val="target" />
				<sval type="string" val="flags" />
				<sval type="string" val="station" />
				<sval type="string" val="OCVcapships" />
				<sval type="string" val="xenonCapships" />
			</sval>
			<sval type="array" size="119">
				<sval type="array" size="2">
					<sval type="int" val="101" />
					<sval type="string" val="WaitForUniverseGeneration" />
				</sval>
				<sval type="array" size="4">
					<sval type="int" val="158" />
					<sval type="int" val="5" />
					<sval type="string" val="mayhem_startingOptionDone" />
					<sval type="int" val="0" />
				</sval>
				<sval type="array" size="10">
					<sval type="int" val="104" />
					<sval type="int" val="-1610611453" />
					<sval type="int" val="2" />
					<sval type="int" val="131074" />
					<sval type="int" val="0" />
					<sval type="int" val="15" />
					<sval type="int" val="65556" />
					<sval type="int" val="2" />
					<sval type="int" val="65556" />
					<sval type="int" val="-1" />
				</sval>
				<sval type="array" size="4">
					<sval type="int" val="105" />
					<sval type="int" val="-2147483647" />
					<sval type="int" val="4" />
					<sval type="int" val="60000" />
				</sval>
				<sval type="array" size="2">
					<sval type="int" val="100" />
					<sval type="int" val="0" />
				</sval>
				<sval type="array" size="4">
					<sval type="int" val="158" />
					<sval type="int" val="5" />
					<sval type="string" val="mayhem_startingOptionAnswers" />
					<sval type="int" val="1" />
				</sval>
				<sval type="array" size="6">
					<sval type="int" val="1709" />
					<sval type="int" val="2" />
					<sval type="int" val="131074" />
					<sval type="int" val="1" />
					<sval type="int" val="5" />
					<sval type="string" val="ocvDifficulty" />
				</sval>
				<sval type="array" size="4">
					<sval type="int" val="706" />
					<sval type="int" val="131075" />
					<sval type="int" val="1" />
					<sval type="int" val="-1610584055" />
				</sval>
				<sval type="array" size="2">
					<sval type="int" val="101" />
					<sval type="string" val="Restart" />
				</sval>
				<sval type="array" size="2">
					<sval type="int" val="1201" />
					<sval type="int" val="-1610609149" />
				</sval>
				<sval type="array" size="2">
					<sval type="int" val="1032" />
					<sval type="int" val="3" />
				</sval>
				<sval type="array" size="2">
					<sval type="int" val="147" />
					<sval type="int" val="4" />
				</sval>
				<sval type="array" size="26">
					<sval type="int" val="102" />
					<sval type="string" val="Lib.Gen.RunScriptWhenFinished" />
					<sval type="int" val="-2147483646" />
					<sval type="int" val="131075" />
					<sval type="int" val="12" />
					<sval type="int" val="10" />
					<sval type="int" val="131074" />
					<sval type="int" val="3" />
					<sval type="int" val="131074" />
					<sval type="int" val="4" />
					<sval type="int" val="131074" />
					<sval type="int" val="4" />
					<sval type="int" val="131075" />
					<sval type="int" val="1" />
					<sval type="int" val="131075" />
					<sval type="int" val="1" />
					<sval type="int" val="0" />
					<sval type="int" val="0" />
					<sval type="int" val="0" />
					<sval type="int" val="0" />
					<sval type="int" val="0" />
					<sval type="int" val="0" />
					<sval type="int" val="0" />
					<sval type="int" val="0" />
					<sval type="int" val="0" />
					<sval type="int" val="0" />
				</sval>
				<sval type="array" size="3">
					<sval type="int" val="103" />
					<sval type="int" val="0" />
					<sval type="int" val="0" />
				</sval>
				<sval type="array" size="6">
					<sval type="int" val="107" />
					<sval type="int" val="-2147483647" />
					<sval type="int" val="4" />
					<sval type="int" val="3000" />
					<sval type="int" val="4" />
					<sval type="int" val="4000" />
				</sval>
				<sval type="array" size="4">
					<sval type="int" val="158" />
					<sval type="int" val="5" />
					<sval type="string" val="ZH_OCVgrinding" />
					<sval type="int" val="5" />
				</sval>
				<sval type="array" size="6">
					<sval type="int" val="110" />
					<sval type="int" val="6" />
					<sval type="int" val="4" />
					<sval type="int" val="1" />
					<sval type="int" val="4" />
					<sval type="int" val="101" />
				</sval>
				<sval type="array" size="7">
					<sval type="int" val="104" />
					<sval type="int" val="-1610607864" />
					<sval type="int" val="1" />
					<sval type="int" val="131074" />
					<sval type="int" val="5" />
					<sval type="int" val="1" />
					<sval type="int" val="-1" />
				</sval>
				<sval type="array" size="7">
					<sval type="int" val="104" />
					<sval type="int" val="6" />
					<sval type="int" val="1" />
					<sval type="int" val="4" />
					<sval type="int" val="1" />
					<sval type="int" val="1" />
					<sval type="int" val="-1" />
				</sval>
				<sval type="array" size="13">
					<sval type="int" val="104" />
					<sval type="int" val="-1610607101" />
					<sval type="int" val="3" />
					<sval type="int" val="131074" />
					<sval type="int" val="2" />
					<sval type="int" val="4" />
					<sval type="int" val="2" />
					<sval type="int" val="15" />
					<sval type="int" val="4" />
					<sval type="int" val="3" />
					<sval type="int" val="-1" />
					<sval type="int" val="4" />
					<sval type="int" val="-2" />
				</sval>
				<sval type="array" size="13">
					<sval type="int" val="104" />
					<sval type="int" val="6" />
					<sval type="int" val="3" />
					<sval type="int" val="131074" />
					<sval type="int" val="6" />
					<sval type="int" val="4" />
					<sval type="int" val="20" />
					<sval type="int" val="15" />
					<sval type="int" val="11" />
					<sval type="int" val="3" />
					<sval type="int" val="-1" />
					<sval type="int" val="11" />
					<sval type="int" val="-2" />
				</sval>
				<sval type="array" size="2">
					<sval type="int" val="112" />
					<sval type="int" val="25" />
				</sval>
				<sval type="array" size="13">
					<sval type="int" val="104" />
					<sval type="int" val="-1610606331" />
					<sval type="int" val="3" />
					<sval type="int" val="131074" />
					<sval type="int" val="2" />
					<sval type="int" val="4" />
					<sval type="int" val="0" />
					<sval type="int" val="15" />
					<sval type="int" val="0" />
					<sval type="int" val="3" />
					<sval type="int" val="-1" />
					<sval type="int" val="0" />
					<sval type="int" val="-2" />
				</sval>
				<sval type="array" size="4">
					<sval type="int" val="106" />
					<sval type="int" val="-536864505" />
					<sval type="int" val="4" />
					<sval type="int" val="4" />
				</sval>
				<sval type="array" size="7">
					<sval type="int" val="104" />
					<sval type="int" val="6" />
					<sval type="int" val="1" />
					<sval type="int" val="4" />
					<sval type="int" val="1" />
					<sval type="int" val="1" />
					<sval type="int" val="-1" />
				</sval>
				<sval type="array" size="13">
					<sval type="int" val="104" />
					<sval type="int" val="-1610605565" />
					<sval type="int" val="3" />
					<sval type="int" val="131074" />
					<sval type="int" val="6" />
					<sval type="int" val="4" />
					<sval type="int" val="90" />
					<sval type="int" val="15" />
					<sval type="int" val="4" />
					<sval type="int" val="3" />
					<sval type="int" val="-1" />
					<sval type="int" val="4" />
					<sval type="int" val="-2" />
				</sval>
				<sval type="array" size="7">
					<sval type="int" val="104" />
					<sval type="int" val="7" />
					<sval type="int" val="1" />
					<sval type="int" val="4" />
					<sval type="int" val="8" />
					<sval type="int" val="1" />
					<sval type="int" val="-1" />
				</sval>
				<sval type="array" size="2">
					<sval type="int" val="112" />
					<sval type="int" val="35" />
				</sval>
				<sval type="array" size="13">
					<sval type="int" val="104" />
					<sval type="int" val="-1610604795" />
					<sval type="int" val="3" />
					<sval type="int" val="131074" />
					<sval type="int" val="6" />
					<sval type="int" val="4" />
					<sval type="int" val="80" />
					<sval type="int" val="15" />
					<sval type="int" val="4" />
					<sval type="int" val="3" />
					<sval type="int" val="-1" />
					<sval type="int" val="4" />
					<sval type="int" val="-2" />
				</sval>
				<sval type="array" size="7">
					<sval type="int" val="104" />
					<sval type="int" val="7" />
					<sval type="int" val="1" />
					<sval type="int" val="4" />
					<sval type="int" val="4" />
					<sval type="int" val="1" />
					<sval type="int" val="-1" />
				</sval>
				<sval type="array" size="2">
					<sval type="int" val="112" />
					<sval type="int" val="35" />
				</sval>
				<sval type="array" size="13">
					<sval type="int" val="104" />
					<sval type="int" val="-1610604027" />
					<sval type="int" val="3" />
					<sval type="int" val="131074" />
					<sval type="int" val="6" />
					<sval type="int" val="4" />
					<sval type="int" val="60" />
					<sval type="int" val="15" />
					<sval type="int" val="4" />
					<sval type="int" val="3" />
					<sval type="int" val="-1" />
					<sval type="int" val="4" />
					<sval type="int" val="-2" />
				</sval>
				<sval type="array" size="7">
					<sval type="int" val="104" />
					<sval type="int" val="7" />
					<sval type="int" val="1" />
					<sval type="int" val="4" />
					<sval type="int" val="2" />
					<sval type="int" val="1" />
					<sval type="int" val="-1" />
				</sval>
				<sval type="array" size="2">
					<sval type="int" val="112" />
					<sval type="int" val="35" />
				</sval>
				<sval type="array" size="7">
					<sval type="int" val="104" />
					<sval type="int" val="7" />
					<sval type="int" val="1" />
					<sval type="int" val="4" />
					<sval type="int" val="1" />
					<sval type="int" val="1" />
					<sval type="int" val="-1" />
				</sval>
				<sval type="array" size="13">
					<sval type="int" val="104" />
					<sval type="int" val="-1610603005" />
					<sval type="int" val="3" />
					<sval type="int" val="131074" />
					<sval type="int" val="2" />
					<sval type="int" val="4" />
					<sval type="int" val="2" />
					<sval type="int" val="15" />
					<sval type="int" val="4" />
					<sval type="int" val="3" />
					<sval type="int" val="-1" />
					<sval type="int" val="4" />
					<sval type="int" val="-2" />
				</sval>
				<sval type="array" size="13">
					<sval type="int" val="104" />
					<sval type="int" val="7" />
					<sval type="int" val="3" />
					<sval type="int" val="131074" />
					<sval type="int" val="7" />
					<sval type="int" val="4" />
					<sval type="int" val="1" />
					<sval type="int" val="15" />
					<sval type="int" val="11" />
					<sval type="int" val="3" />
					<sval type="int" val="-1" />
					<sval type="int" val="11" />
					<sval type="int" val="-2" />
				</sval>
				<sval type="array" size="2">
					<sval type="int" val="112" />
					<sval type="int" val="42" />
				</sval>
				<sval type="array" size="13">
					<sval type="int" val="104" />
					<sval type="int" val="-1610601979" />
					<sval type="int" val="3" />
					<sval type="int" val="131074" />
					<sval type="int" val="2" />
					<sval type="int" val="4" />
					<sval type="int" val="0" />
					<sval type="int" val="15" />
					<sval type="int" val="0" />
					<sval type="int" val="3" />
					<sval type="int" val="-1" />
					<sval type="int" val="0" />
					<sval type="int" val="-2" />
				</sval>
				<sval type="array" size="13">
					<sval type="int" val="104" />
					<sval type="int" val="7" />
					<sval type="int" val="3" />
					<sval type="int" val="131074" />
					<sval type="int" val="7" />
					<sval type="int" val="4" />
					<sval type="int" val="2" />
					<sval type="int" val="15" />
					<sval type="int" val="14" />
					<sval type="int" val="3" />
					<sval type="int" val="-1" />
					<sval type="int" val="14" />
					<sval type="int" val="-2" />
				</sval>
				<sval type="array" size="7">
					<sval type="int" val="104" />
					<sval type="int" val="-536860153" />
					<sval type="int" val="1" />
					<sval type="int" val="131074" />
					<sval type="int" val="7" />
					<sval type="int" val="1" />
					<sval type="int" val="-1" />
				</sval>
				<sval type="array" size="7">
					<sval type="int" val="104" />
					<sval type="int" val="7" />
					<sval type="int" val="1" />
					<sval type="int" val="4" />
					<sval type="int" val="1" />
					<sval type="int" val="1" />
					<sval type="int" val="-1" />
				</sval>
				<sval type="array" size="7">
					<sval type="int" val="104" />
					<sval type="int" val="8" />
					<sval type="int" val="1" />
					<sval type="int" val="0" />
					<sval type="int" val="0" />
					<sval type="int" val="1" />
					<sval type="int" val="-1" />
				</sval>
				<sval type="array" size="2">
					<sval type="int" val="101" />
					<sval type="string" val="SearchSector" />
				</sval>
				<sval type="array" size="8">
					<sval type="int" val="1334" />
					<sval type="int" val="131075" />
					<sval type="int" val="1" />
					<sval type="int" val="9" />
					<sval type="int" val="131074" />
					<sval type="int" val="7" />
					<sval type="int" val="131075" />
					<sval type="int" val="9" />
				</sval>
				<sval type="array" size="8">
					<sval type="int" val="102" />
					<sval type="string" val="Joubarbe.Lib.RandomizeArray" />
					<sval type="int" val="9" />
					<sval type="int" val="131075" />
					<sval type="int" val="12" />
					<sval type="int" val="1" />
					<sval type="int" val="131074" />
					<sval type="int" val="9" />
				</sval>
				<sval type="array" size="4">
					<sval type="int" val="131" />
					<sval type="int" val="11" />
					<sval type="int" val="131074" />
					<sval type="int" val="9" />
				</sval>
				<sval type="array" size="7">
					<sval type="int" val="104" />
					<sval type="int" val="-1610596087" />
					<sval type="int" val="1" />
					<sval type="int" val="131074" />
					<sval type="int" val="11" />
					<sval type="int" val="1" />
					<sval type="int" val="-1" />
				</sval>
				<sval type="array" size="2">
					<sval type="int" val="143" />
					<sval type="int" val="11" />
				</sval>
				<sval type="array" size="6">
					<sval type="int" val="129" />
					<sval type="int" val="10" />
					<sval type="int" val="131074" />
					<sval type="int" val="9" />
					<sval type="int" val="131074" />
					<sval type="int" val="11" />
				</sval>
				<sval type="array" size="4">
					<sval type="int" val="701" />
					<sval type="int" val="131074" />
					<sval type="int" val="10" />
					<sval type="int" val="12" />
				</sval>
				<sval type="array" size="13">
					<sval type="int" val="104" />
					<sval type="int" val="-1610599160" />
					<sval type="int" val="3" />
					<sval type="int" val="131074" />
					<sval type="int" val="12" />
					<sval type="int" val="10" />
					<sval type="int" val="6" />
					<sval type="int" val="15" />
					<sval type="int" val="0" />
					<sval type="int" val="3" />
					<sval type="int" val="-1" />
					<sval type="int" val="0" />
					<sval type="int" val="-2" />
				</sval>
				<sval type="array" size="2">
					<sval type="int" val="112" />
					<sval type="int" val="47" />
				</sval>
				<sval type="array" size="13">
					<sval type="int" val="104" />
					<sval type="int" val="-1610597629" />
					<sval type="int" val="3" />
					<sval type="int" val="131074" />
					<sval type="int" val="7" />
					<sval type="int" val="4" />
					<sval type="int" val="1" />
					<sval type="int" val="15" />
					<sval type="int" val="2" />
					<sval type="int" val="3" />
					<sval type="int" val="-1" />
					<sval type="int" val="2" />
					<sval type="int" val="-2" />
				</sval>
				<sval type="array" size="13">
					<sval type="int" val="104" />
					<sval type="int" val="-1610597629" />
					<sval type="int" val="3" />
					<sval type="int" val="131074" />
					<sval type="int" val="12" />
					<sval type="int" val="10" />
					<sval type="int" val="10" />
					<sval type="int" val="15" />
					<sval type="int" val="0" />
					<sval type="int" val="3" />
					<sval type="int" val="-1" />
					<sval type="int" val="0" />
					<sval type="int" val="-2" />
				</sval>
				<sval type="array" size="10">
					<sval type="int" val="102" />
					<sval type="string" val="Mayhem.GetOwnedSectors" />
					<sval type="int" val="13" />
					<sval type="int" val="131075" />
					<sval type="int" val="12" />
					<sval type="int" val="2" />
					<sval type="int" val="10" />
					<sval type="int" val="10" />
					<sval type="int" val="131075" />
					<sval type="int" val="9" />
				</sval>
				<sval type="array" size="4">
					<sval type="int" val="131" />
					<sval type="int" val="14" />
					<sval type="int" val="131074" />
					<sval type="int" val="13" />
				</sval>
				<sval type="array" size="13">
					<sval type="int" val="104" />
					<sval type="int" val="-536855801" />
					<sval type="int" val="3" />
					<sval type="int" val="131074" />
					<sval type="int" val="14" />
					<sval type="int" val="4" />
					<sval type="int" val="9" />
					<sval type="int" val="15" />
					<sval type="int" val="2" />
					<sval type="int" val="3" />
					<sval type="int" val="-1" />
					<sval type="int" val="2" />
					<sval type="int" val="-2" />
				</sval>
				<sval type="array" size="2">
					<sval type="int" val="112" />
					<sval type="int" val="47" />
				</sval>
				<sval type="array" size="2">
					<sval type="int" val="1167" />
					<sval type="int" val="113" />
				</sval>
				<sval type="array" size="22">
					<sval type="int" val="104" />
					<sval type="int" val="-1610596856" />
					<sval type="int" val="6" />
					<sval type="int" val="131074" />
					<sval type="int" val="15" />
					<sval type="int" val="4" />
					<sval type="int" val="2" />
					<sval type="int" val="15" />
					<sval type="int" val="2" />
					<sval type="int" val="131074" />
					<sval type="int" val="5" />
					<sval type="int" val="15" />
					<sval type="int" val="65556" />
					<sval type="int" val="15" />
					<sval type="int" val="9" />
					<sval type="int" val="6" />
					<sval type="int" val="-1" />
					<sval type="int" val="2" />
					<sval type="int" val="-2" />
					<sval type="int" val="9" />
					<sval type="int" val="65556" />
					<sval type="int" val="-4" />
				</sval>
				<sval type="array" size="2">
					<sval type="int" val="112" />
					<sval type="int" val="47" />
				</sval>
				<sval type="array" size="7">
					<sval type="int" val="104" />
					<sval type="int" val="8" />
					<sval type="int" val="1" />
					<sval type="int" val="131074" />
					<sval type="int" val="10" />
					<sval type="int" val="1" />
					<sval type="int" val="-1" />
				</sval>
				<sval type="array" size="2">
					<sval type="int" val="112" />
					<sval type="int" val="65" />
				</sval>
				<sval type="array" size="2">
					<sval type="int" val="112" />
					<sval type="int" val="47" />
				</sval>
				<sval type="array" size="10">
					<sval type="int" val="104" />
					<sval type="int" val="-1610594557" />
					<sval type="int" val="2" />
					<sval type="int" val="131074" />
					<sval type="int" val="8" />
					<sval type="int" val="15" />
					<sval type="int" val="65556" />
					<sval type="int" val="2" />
					<sval type="int" val="65556" />
					<sval type="int" val="-1" />
				</sval>
				<sval type="array" size="13">
					<sval type="int" val="104" />
					<sval type="int" val="-1610595069" />
					<sval type="int" val="3" />
					<sval type="int" val="131074" />
					<sval type="int" val="7" />
					<sval type="int" val="4" />
					<sval type="int" val="30" />
					<sval type="int" val="15" />
					<sval type="int" val="2" />
					<sval type="int" val="3" />
					<sval type="int" val="-1" />
					<sval type="int" val="2" />
					<sval type="int" val="-2" />
				</sval>
				<sval type="array" size="10">
					<sval type="int" val="102" />
					<sval type="string" val="!fight.defend.sector" />
					<sval type="int" val="-2147483647" />
					<sval type="int" val="131075" />
					<sval type="int" val="1" />
					<sval type="int" val="2" />
					<sval type="int" val="131075" />
					<sval type="int" val="6" />
					<sval type="int" val="4" />
					<sval type="int" val="1800" />
				</sval>
				<sval type="array" size="2">
					<sval type="int" val="100" />
					<sval type="int" val="8" />
				</sval>
				<sval type="array" size="2">
					<sval type="int" val="142" />
					<sval type="int" val="7" />
				</sval>
				<sval type="array" size="2">
					<sval type="int" val="100" />
					<sval type="int" val="43" />
				</sval>
				<sval type="array" size="13">
					<sval type="int" val="104" />
					<sval type="int" val="-1610593527" />
					<sval type="int" val="3" />
					<sval type="int" val="131075" />
					<sval type="int" val="6" />
					<sval type="int" val="131074" />
					<sval type="int" val="8" />
					<sval type="int" val="15" />
					<sval type="int" val="1" />
					<sval type="int" val="3" />
					<sval type="int" val="-1" />
					<sval type="int" val="1" />
					<sval type="int" val="-2" />
				</sval>
				<sval type="array" size="8">
					<sval type="int" val="102" />
					<sval type="string" val="!move.movetosector" />
					<sval type="int" val="-2147483647" />
					<sval type="int" val="131075" />
					<sval type="int" val="1" />
					<sval type="int" val="1" />
					<sval type="int" val="131074" />
					<sval type="int" val="8" />
				</sval>
				<sval type="array" size="4">
					<sval type="int" val="105" />
					<sval type="int" val="-2147483647" />
					<sval type="int" val="4" />
					<sval type="int" val="1000" />
				</sval>
				<sval type="array" size="2">
					<sval type="int" val="112" />
					<sval type="int" val="71" />
				</sval>
				<sval type="array" size="2">
					<sval type="int" val="1167" />
					<sval type="int" val="113" />
				</sval>
				<sval type="array" size="4">
					<sval type="int" val="131" />
					<sval type="int" val="18" />
					<sval type="int" val="131074" />
					<sval type="int" val="17" />
				</sval>
				<sval type="array" size="7">
					<sval type="int" val="104" />
					<sval type="int" val="-1610590455" />
					<sval type="int" val="1" />
					<sval type="int" val="131074" />
					<sval type="int" val="18" />
					<sval type="int" val="1" />
					<sval type="int" val="-1" />
				</sval>
				<sval type="array" size="2">
					<sval type="int" val="143" />
					<sval type="int" val="18" />
				</sval>
				<sval type="array" size="6">
					<sval type="int" val="129" />
					<sval type="int" val="16" />
					<sval type="int" val="131074" />
					<sval type="int" val="17" />
					<sval type="int" val="131074" />
					<sval type="int" val="18" />
				</sval>
				<sval type="array" size="4">
					<sval type="int" val="105" />
					<sval type="int" val="-2147483647" />
					<sval type="int" val="4" />
					<sval type="int" val="100" />
				</sval>
				<sval type="array" size="4">
					<sval type="int" val="106" />
					<sval type="int" val="-1610590717" />
					<sval type="int" val="131074" />
					<sval type="int" val="15" />
				</sval>
				<sval type="array" size="7">
					<sval type="int" val="1072" />
					<sval type="int" val="131074" />
					<sval type="int" val="16" />
					<sval type="int" val="-1610591224" />
					<sval type="string" val="Mayhem.Task.OCVInvader.Leader" />
					<sval type="int" val="4" />
					<sval type="int" val="0" />
				</sval>
				<sval type="array" size="2">
					<sval type="int" val="100" />
					<sval type="int" val="43" />
				</sval>
				<sval type="array" size="7">
					<sval type="int" val="1072" />
					<sval type="int" val="131074" />
					<sval type="int" val="16" />
					<sval type="int" val="-1610590712" />
					<sval type="string" val="Mayhem.Task.XenonInvader.Leader" />
					<sval type="int" val="4" />
					<sval type="int" val="0" />
				</sval>
				<sval type="array" size="2">
					<sval type="int" val="100" />
					<sval type="int" val="43" />
				</sval>
				<sval type="array" size="2">
					<sval type="int" val="112" />
					<sval type="int" val="77" />
				</sval>
				<sval type="array" size="2">
					<sval type="int" val="101" />
					<sval type="string" val="SearchTarget" />
				</sval>
				<sval type="array" size="6">
					<sval type="int" val="110" />
					<sval type="int" val="19" />
					<sval type="int" val="4" />
					<sval type="int" val="150" />
					<sval type="int" val="4" />
					<sval type="int" val="451" />
				</sval>
				<sval type="array" size="7">
					<sval type="int" val="104" />
					<sval type="int" val="-536847356" />
					<sval type="int" val="1" />
					<sval type="int" val="131074" />
					<sval type="int" val="5" />
					<sval type="int" val="1" />
					<sval type="int" val="-1" />
				</sval>
				<sval type="array" size="4">
					<sval type="int" val="706" />
					<sval type="int" val="131074" />
					<sval type="int" val="20" />
					<sval type="int" val="-536847353" />
				</sval>
				<sval type="array" size="10">
					<sval type="int" val="102" />
					<sval type="string" val="!fight.defend.sector" />
					<sval type="int" val="-2147483647" />
					<sval type="int" val="131075" />
					<sval type="int" val="1" />
					<sval type="int" val="2" />
					<sval type="int" val="131075" />
					<sval type="int" val="6" />
					<sval type="int" val="131074" />
					<sval type="int" val="19" />
				</sval>
				<sval type="array" size="13">
					<sval type="int" val="104" />
					<sval type="int" val="21" />
					<sval type="int" val="3" />
					<sval type="int" val="131075" />
					<sval type="int" val="106" />
					<sval type="int" val="131075" />
					<sval type="int" val="108" />
					<sval type="int" val="15" />
					<sval type="int" val="7" />
					<sval type="int" val="3" />
					<sval type="int" val="-1" />
					<sval type="int" val="7" />
					<sval type="int" val="-2" />
				</sval>
				<sval type="array" size="4">
					<sval type="int" val="706" />
					<sval type="int" val="131074" />
					<sval type="int" val="20" />
					<sval type="int" val="-536846585" />
				</sval>
				<sval type="array" size="18">
					<sval type="int" val="794" />
					<sval type="int" val="20" />
					<sval type="int" val="131075" />
					<sval type="int" val="6" />
					<sval type="int" val="12" />
					<sval type="int" val="2006" />
					<sval type="int" val="0" />
					<sval type="int" val="0" />
					<sval type="int" val="131074" />
					<sval type="int" val="21" />
					<sval type="int" val="131075" />
					<sval type="int" val="1" />
					<sval type="int" val="4" />
					<sval type="int" val="300000" />
					<sval type="int" val="4" />
					<sval type="int" val="1" />
					<sval type="int" val="0" />
					<sval type="int" val="0" />
				</sval>
				<sval type="array" size="4">
					<sval type="int" val="105" />
					<sval type="int" val="-2147483647" />
					<sval type="int" val="4" />
					<sval type="int" val="100" />
				</sval>
				<sval type="array" size="4">
					<sval type="int" val="706" />
					<sval type="int" val="131074" />
					<sval type="int" val="20" />
					<sval type="int" val="-536845817" />
				</sval>
				<sval type="array" size="18">
					<sval type="int" val="794" />
					<sval type="int" val="20" />
					<sval type="int" val="131075" />
					<sval type="int" val="6" />
					<sval type="int" val="0" />
					<sval type="int" val="0" />
					<sval type="int" val="0" />
					<sval type="int" val="0" />
					<sval type="int" val="131074" />
					<sval type="int" val="21" />
					<sval type="int" val="131075" />
					<sval type="int" val="1" />
					<sval type="int" val="4" />
					<sval type="int" val="300000" />
					<sval type="int" val="4" />
					<sval type="int" val="1" />
					<sval type="int" val="0" />
					<sval type="int" val="0" />
				</sval>
				<sval type="array" size="4">
					<sval type="int" val="706" />
					<sval type="int" val="131074" />
					<sval type="int" val="20" />
					<sval type="int" val="-1610586621" />
				</sval>
				<sval type="array" size="14">
					<sval type="int" val="102" />
					<sval type="string" val="!fight.attack.object" />
					<sval type="int" val="-2147483647" />
					<sval type="int" val="131075" />
					<sval type="int" val="1" />
					<sval type="int" val="4" />
					<sval type="int" val="131074" />
					<sval type="int" val="20" />
					<sval type="int" val="131075" />
					<sval type="int" val="9" />
					<sval type="int" val="131075" />
					<sval type="int" val="9" />
					<sval type="int" val="4" />
					<sval type="int" val="3600" />
				</sval>
				<sval type="array" size="2">
					<sval type="int" val="100" />
					<sval type="int" val="87" />
				</sval>
				<sval type="array" size="2">
					<sval type="int" val="112" />
					<sval type="int" val="111" />
				</sval>
				<sval type="array" size="4">
					<sval type="int" val="701" />
					<sval type="int" val="131075" />
					<sval type="int" val="6" />
					<sval type="int" val="12" />
				</sval>
				<sval type="array" size="13">
					<sval type="int" val="104" />
					<sval type="int" val="-1610585853" />
					<sval type="int" val="3" />
					<sval type="int" val="131074" />
					<sval type="int" val="12" />
					<sval type="int" val="10" />
					<sval type="int" val="6" />
					<sval type="int" val="15" />
					<sval type="int" val="1" />
					<sval type="int" val="3" />
					<sval type="int" val="-1" />
					<sval type="int" val="1" />
					<sval type="int" val="-2" />
				</sval>
				<sval type="array" size="10">
					<sval type="int" val="102" />
					<sval type="string" val="Mayhem.Conquer" />
					<sval type="int" val="-2147483647" />
					<sval type="int" val="131075" />
					<sval type="int" val="12" />
					<sval type="int" val="2" />
					<sval type="int" val="131075" />
					<sval type="int" val="6" />
					<sval type="int" val="10" />
					<sval type="int" val="6" />
				</sval>
				<sval type="array" size="18">
					<sval type="int" val="794" />
					<sval type="int" val="-536843513" />
					<sval type="int" val="131075" />
					<sval type="int" val="6" />
					<sval type="int" val="9" />
					<sval type="int" val="327685" />
					<sval type="int" val="10" />
					<sval type="int" val="6" />
					<sval type="int" val="4" />
					<sval type="int" val="0" />
					<sval type="int" val="0" />
					<sval type="int" val="0" />
					<sval type="int" val="4" />
					<sval type="int" val="0" />
					<sval type="int" val="4" />
					<sval type="int" val="1" />
					<sval type="int" val="0" />
					<sval type="int" val="0" />
				</sval>
				<sval type="array" size="16">
					<sval type="int" val="102" />
					<sval type="string" val="Mayhem.BuildStationAI" />
					<sval type="int" val="22" />
					<sval type="int" val="131075" />
					<sval type="int" val="12" />
					<sval type="int" val="5" />
					<sval type="int" val="9" />
					<sval type="int" val="327685" />
					<sval type="int" val="10" />
					<sval type="int" val="6" />
					<sval type="int" val="131075" />
					<sval type="int" val="6" />
					<sval type="int" val="0" />
					<sval type="int" val="0" />
					<sval type="int" val="0" />
					<sval type="int" val="0" />
				</sval>
				<sval type="array" size="7">
					<sval type="int" val="104" />
					<sval type="int" val="-1610584573" />
					<sval type="int" val="1" />
					<sval type="int" val="131074" />
					<sval type="int" val="5" />
					<sval type="int" val="1" />
					<sval type="int" val="-1" />
				</sval>
				<sval type="array" size="10">
					<sval type="int" val="102" />
					<sval type="string" val="!fight.defend.sector" />
					<sval type="int" val="-2147483647" />
					<sval type="int" val="131075" />
					<sval type="int" val="1" />
					<sval type="int" val="2" />
					<sval type="int" val="131075" />
					<sval type="int" val="6" />
					<sval type="int" val="4" />
					<sval type="int" val="120" />
				</sval>
				<sval type="array" size="2">
					<sval type="int" val="112" />
					<sval type="int" val="111" />
				</sval>
				<sval type="array" size="10">
					<sval type="int" val="102" />
					<sval type="string" val="!fight.defend.sector" />
					<sval type="int" val="-2147483647" />
					<sval type="int" val="131075" />
					<sval type="int" val="1" />
					<sval type="int" val="2" />
					<sval type="int" val="131075" />
					<sval type="int" val="6" />
					<sval type="int" val="4" />
					<sval type="int" val="3600" />
				</sval>
				<sval type="array" size="2">
					<sval type="int" val="112" />
					<sval type="int" val="7" />
				</sval>
				<sval type="array" size="3">
					<sval type="int" val="103" />
					<sval type="int" val="0" />
					<sval type="int" val="0" />
				</sval>
				<sval type="array" size="2">
					<sval type="int" val="101" />
					<sval type="string" val="CheckTerraformerCapships" />
				</sval>
				<sval type="array" size="12">
					<sval type="int" val="102" />
					<sval type="string" val="Joubarbe.Lib.GetAllShipsFromSector" />
					<sval type="int" val="23" />
					<sval type="int" val="131075" />
					<sval type="int" val="12" />
					<sval type="int" val="3" />
					<sval type="int" val="131074" />
					<sval type="int" val="10" />
					<sval type="int" val="10" />
					<sval type="int" val="16" />
					<sval type="int" val="12" />
					<sval type="int" val="2019" />
				</sval>
				<sval type="array" size="12">
					<sval type="int" val="102" />
					<sval type="string" val="Joubarbe.Lib.GetAllShipsFromSector" />
					<sval type="int" val="24" />
					<sval type="int" val="131075" />
					<sval type="int" val="12" />
					<sval type="int" val="3" />
					<sval type="int" val="131074" />
					<sval type="int" val="10" />
					<sval type="int" val="10" />
					<sval type="int" val="6" />
					<sval type="int" val="12" />
					<sval type="int" val="2019" />
				</sval>
				<sval type="array" size="6">
					<sval type="int" val="1850" />
					<sval type="int" val="17" />
					<sval type="int" val="131074" />
					<sval type="int" val="23" />
					<sval type="int" val="131074" />
					<sval type="int" val="24" />
				</sval>
				<sval type="array" size="4">
					<sval type="int" val="131" />
					<sval type="int" val="15" />
					<sval type="int" val="131074" />
					<sval type="int" val="17" />
				</sval>
				<sval type="array" size="1">
					<sval type="int" val="1168" />
				</sval>
			</sval>
			<sval type="int" val="0" />
			<sval type="array" size="61">
				<sval type="array" size="2">
					<sval type="int" val="0" />
					<sval type="int" val="2" />
				</sval>
				<sval type="array" size="3">
					<sval type="int" val="0" />
					<sval type="int" val="1" />
					<sval type="string" val="Task 0." />
				</sval>
				<sval type="array" size="2">
					<sval type="int" val="0" />
					<sval type="int" val="2" />
				</sval>
				<sval type="array" size="3">
					<sval type="int" val="0" />
					<sval type="int" val="1" />
					<sval type="string" val="OCV invades all sectors and put Xenon stations in them, leading to new Xenon invasions." />
				</sval>
				<sval type="array" size="3">
					<sval type="int" val="0" />
					<sval type="int" val="1" />
					<sval type="string" val="in Zero Hour mod they slowly spread out from the OCV portal and don't focus on higher abnormal signal sectors" />
				</sval>
				<sval type="array" size="2">
					<sval type="int" val="0" />
					<sval type="int" val="2" />
				</sval>
				<sval type="array" size="3">
					<sval type="int" val="0" />
					<sval type="int" val="1" />
					<sval type="string" val="Zero Hour: hard difficulty modifies OCV deep strike invasion chance and galaxy range" />
				</sval>
				<sval type="array" size="2">
					<sval type="int" val="5" />
					<sval type="int" val="4" />
				</sval>
				<sval type="array" size="2">
					<sval type="int" val="7" />
					<sval type="int" val="2" />
				</sval>
				<sval type="array" size="2">
					<sval type="int" val="8" />
					<sval type="int" val="2" />
				</sval>
				<sval type="array" size="2">
					<sval type="int" val="9" />
					<sval type="int" val="2" />
				</sval>
				<sval type="array" size="2">
					<sval type="int" val="14" />
					<sval type="int" val="4" />
				</sval>
				<sval type="array" size="2">
					<sval type="int" val="14" />
					<sval type="int" val="2" />
				</sval>
				<sval type="array" size="2">
					<sval type="int" val="15" />
					<sval type="int" val="2" />
				</sval>
				<sval type="array" size="2">
					<sval type="int" val="16" />
					<sval type="int" val="2" />
				</sval>
				<sval type="array" size="3">
					<sval type="int" val="18" />
					<sval type="int" val="1" />
					<sval type="string" val="no deep strikes if the OCV is grinding" />
				</sval>
				<sval type="array" size="2">
					<sval type="int" val="25" />
					<sval type="int" val="4" />
				</sval>
				<sval type="array" size="2">
					<sval type="int" val="34" />
					<sval type="int" val="5" />
				</sval>
				<sval type="array" size="2">
					<sval type="int" val="35" />
					<sval type="int" val="4" />
				</sval>
				<sval type="array" size="2">
					<sval type="int" val="42" />
					<sval type="int" val="4" />
				</sval>
				<sval type="array" size="2">
					<sval type="int" val="53" />
					<sval type="int" val="6" />
				</sval>
				<sval type="array" size="3">
					<sval type="int" val="54" />
					<sval type="int" val="1" />
					<sval type="string" val="the random long range strikes cannot target the player if his empire is still small. Otherwise bad luck could make it impossible to prevent" />
				</sval>
				<sval type="array" size="2">
					<sval type="int" val="59" />
					<sval type="int" val="6" />
				</sval>
				<sval type="array" size="2">
					<sval type="int" val="59" />
					<sval type="int" val="4" />
				</sval>
				<sval type="array" size="2">
					<sval type="int" val="59" />
					<sval type="int" val="4" />
				</sval>
				<sval type="array" size="3">
					<sval type="int" val="60" />
					<sval type="int" val="1" />
					<sval type="string" val="we don't want too many invader fleets in one sector (undefeatable doomstack) unless the OCV is grinding" />
				</sval>
				<sval type="array" size="2">
					<sval type="int" val="62" />
					<sval type="int" val="6" />
				</sval>
				<sval type="array" size="2">
					<sval type="int" val="64" />
					<sval type="int" val="7" />
				</sval>
				<sval type="array" size="2">
					<sval type="int" val="65" />
					<sval type="int" val="4" />
				</sval>
				<sval type="array" size="2">
					<sval type="int" val="69" />
					<sval type="int" val="4" />
				</sval>
				<sval type="array" size="2">
					<sval type="int" val="71" />
					<sval type="int" val="4" />
				</sval>
				<sval type="array" size="2">
					<sval type="int" val="71" />
					<sval type="int" val="2" />
				</sval>
				<sval type="array" size="2">
					<sval type="int" val="75" />
					<sval type="int" val="4" />
				</sval>
				<sval type="array" size="2">
					<sval type="int" val="75" />
					<sval type="int" val="2" />
				</sval>
				<sval type="array" size="3">
					<sval type="int" val="75" />
					<sval type="int" val="1" />
					<sval type="string" val="we have reached our invasion target. Now we check if any other invaders came here before us" />
				</sval>
				<sval type="array" size="3">
					<sval type="int" val="82" />
					<sval type="int" val="1" />
					<sval type="string" val="there is always a chance to stay, depending on how many capships are already here. But most of the time we do not want more than 1 OCV invader fleet per sector." />
				</sval>
				<sval type="array" size="2">
					<sval type="int" val="86" />
					<sval type="int" val="4" />
				</sval>
				<sval type="array" size="2">
					<sval type="int" val="87" />
					<sval type="int" val="4" />
				</sval>
				<sval type="array" size="2">
					<sval type="int" val="87" />
					<sval type="int" val="2" />
				</sval>
				<sval type="array" size="3">
					<sval type="int" val="90" />
					<sval type="int" val="1" />
					<sval type="string" val="don't waste time when grinding" />
				</sval>
				<sval type="array" size="2">
					<sval type="int" val="92" />
					<sval type="int" val="4" />
				</sval>
				<sval type="array" size="3">
					<sval type="int" val="93" />
					<sval type="int" val="1" />
					<sval type="string" val="Priorities: Huge ships, Big ships, Factories, Outposts." />
				</sval>
				<sval type="array" size="3">
					<sval type="int" val="93" />
					<sval type="int" val="1" />
					<sval type="string" val="$target = find ship: sector=[SECTOR] class or type=[Huge Ship] race=null flags=$flags refobj=[THIS] maxdist=80000 maxnum=1 refpos=null" />
				</sval>
				<sval type="array" size="3">
					<sval type="int" val="93" />
					<sval type="int" val="1" />
					<sval type="string" val="= wait 100 ms" />
				</sval>
				<sval type="array" size="3">
					<sval type="int" val="93" />
					<sval type="int" val="1" />
					<sval type="string" val="skip if $target-&gt; exists" />
				</sval>
				<sval type="array" size="3">
					<sval type="int" val="93" />
					<sval type="int" val="1" />
					<sval type="string" val="$target = find ship: sector=[SECTOR] class or type=[Big Ship] race=null flags=$flags refobj=[THIS] maxdist=80000 maxnum=1 refpos=null" />
				</sval>
				<sval type="array" size="3">
					<sval type="int" val="93" />
					<sval type="int" val="1" />
					<sval type="string" val="= wait 100 ms" />
				</sval>
				<sval type="array" size="2">
					<sval type="int" val="98" />
					<sval type="int" val="2" />
				</sval>
				<sval type="array" size="2">
					<sval type="int" val="102" />
					<sval type="int" val="5" />
				</sval>
				<sval type="array" size="3">
					<sval type="int" val="104" />
					<sval type="int" val="1" />
					<sval type="string" val="Also see !station.signal.killed." />
				</sval>
				<sval type="array" size="2">
					<sval type="int" val="105" />
					<sval type="int" val="4" />
				</sval>
				<sval type="array" size="3">
					<sval type="int" val="108" />
					<sval type="int" val="1" />
					<sval type="string" val="don't waste time when grinding" />
				</sval>
				<sval type="array" size="2">
					<sval type="int" val="110" />
					<sval type="int" val="5" />
				</sval>
				<sval type="array" size="2">
					<sval type="int" val="111" />
					<sval type="int" val="4" />
				</sval>
				<sval type="array" size="2">
					<sval type="int" val="111" />
					<sval type="int" val="4" />
				</sval>
				<sval type="array" size="2">
					<sval type="int" val="111" />
					<sval type="int" val="2" />
				</sval>
				<sval type="array" size="2">
					<sval type="int" val="112" />
					<sval type="int" val="4" />
				</sval>
				<sval type="array" size="2">
					<sval type="int" val="112" />
					<sval type="int" val="2" />
				</sval>
				<sval type="array" size="2">
					<sval type="int" val="113" />
					<sval type="int" val="2" />
				</sval>
				<sval type="array" size="2">
					<sval type="int" val="113" />
					<sval type="int" val="2" />
				</sval>
				<sval type="array" size="3">
					<sval type="int" val="114" />
					<sval type="int" val="1" />
					<sval type="string" val="Zero Hour: we need to ensure that Terraformer capships tend to spread out and don't create undefeatable doomstacks" />
				</sval>
			</sval>
			<sval type="int" val="0" />
		</sval>
	</codearray>
</script>
